bagulhinho/__init__.py
bagulhinho/cli.py
bagulhinho-0.1.0.dist-info/entry_points.txt
bagulhinho-0.1.0.dist-info/METADATA
bagulhinho-0.1.0.dist-info/WHEEL
bagulhinho-0.1.0.dist-info/RECORD
