Metadata-Version: 2.1
Name: bagulhinho
Version: 0.1.0
Summary: 
Author: leonardo
Author-email: leo-alves14@hotmail.com
Requires-Python: >=3.11,<4.0
Classifier: Programming Language :: Python :: 3
Classifier: Programming Language :: Python :: 3.11
Requires-Dist: httpx (>=0.23.3,<0.24.0)
